mxbids/__init__.py
mxbids/base/__init__.py
mxbids/base/basebidsdirectory.py
mxbids/base/baseexporter.py
mxbids/base/baseimporter.py
mxbids/base/importmaps.py
mxbids/cdfsbids/__init__.py
mxbids/cdfsbids/cdfssession.py
mxbids/cdfsbids/ieegcdfs.py
mxbids/cdfsbids/ieegcdfscomponent.py
mxbids/datasets/__init__.py
mxbids/datasets/dataset.py
mxbids/exporters/__init__.py
mxbids/exporters/bids/__init__.py
mxbids/exporters/bids/anatomybidsexporter.py
mxbids/exporters/bids/ctbidsexporter.py
mxbids/exporters/bids/datasetbidsexporter.py
mxbids/exporters/bids/ieegbidsexporter.py
mxbids/exporters/bids/modalitybidsexporter.py
mxbids/exporters/bids/sessionbidsexporter.py
mxbids/exporters/bids/subjectbidsexporter.py
mxbids/exporters/datasetexporter.py
mxbids/exporters/modalityexporter.py
mxbids/exporters/sessionexporter.py
mxbids/exporters/subjectexporter.py
mxbids/header.py
mxbids/importers/__init__.py
mxbids/importers/bids/__init__.py
mxbids/importers/datasetimporter.py
mxbids/importers/dwi/__init__.py
mxbids/importers/dwi/dwienigmaimporter.py
mxbids/importers/file/__init__.py
mxbids/importers/file/functions.py
mxbids/importers/modalityimporter.py
mxbids/importers/sessionimporter.py
mxbids/importers/subjectimporter.py
mxbids/modalities/__init__.py
mxbids/modalities/anatomy/__init__.py
mxbids/modalities/anatomy/anatomy.py
mxbids/modalities/anatomy/components/__init__.py
mxbids/modalities/ct/__init__.py
mxbids/modalities/ct/components/__init__.py
mxbids/modalities/ct/ct.py
mxbids/modalities/dwi/__init__.py
mxbids/modalities/dwi/components/__init__.py
mxbids/modalities/dwi/dwi.py
mxbids/modalities/ieeg/__init__.py
mxbids/modalities/ieeg/components/__init__.py
mxbids/modalities/ieeg/ieeg.py
mxbids/modalities/modality.py
mxbids/py.typed
mxbids/sessions/__init__.py
mxbids/sessions/session.py
mxbids/subjects/__init__.py
mxbids/subjects/subject.py
mxbids-0.3.0.dist-info/LICENSE.rst
mxbids-0.3.0.dist-info/METADATA
mxbids-0.3.0.dist-info/WHEEL
mxbids-0.3.0.dist-info/entry_points.txt
mxbids-0.3.0.dist-info/RECORD
