Metadata-Version: 2.1
Name: mxbids
Version: 0.3.0
Summary: Modular Extensible Brain Imaging Data Structure
Home-page: https://github.com/fongant/python-mxbids
License: MIT
Author: Anthony Fong
Author-email: FongAnthonyM@gmail.com
Requires-Python: >=3.10,<4.0
Classifier: Development Status :: 3 - Alpha
Classifier: License :: OSI Approved :: MIT License
Classifier: Programming Language :: Python :: 3
Classifier: Programming Language :: Python :: 3.10
Classifier: Programming Language :: Python :: 3.11
Requires-Dist: baseobjects (>=1.11.0)
Requires-Dist: cdfs (>=0.3.0)
Requires-Dist: click (>=8.0.3)
Requires-Dist: hdf5objects (>=0.5.0)
Requires-Dist: pyedflib (>=0.1.36)
Project-URL: Changelog, https://github.com/fongant/python-mxbids/releases
Project-URL: Documentation, https://python-mxbids.readthedocs.io
Project-URL: Repository, https://github.com/fongant/python-mxbids
